bearlib/__init__.py
bearlib/config.py
bearlib/events.py
bearlib/logs.py
bearlib/tools.py
bearlib-0.10.dist-info/LICENSE
bearlib-0.10.dist-info/METADATA
bearlib-0.10.dist-info/WHEEL
bearlib-0.10.dist-info/top_level.txt
bearlib-0.10.dist-info/RECORD
