Metadata-Version: 2.1
Name: bearlib
Version: 0.10
Summary: "bear's toolkit"
Home-page: https://github.com/bear/bearlib
Author: bear (Mike Taylor)
Author-email: bear@bear.im
License: CC0 1.0 Universal
Platform: UNKNOWN
Classifier: Programming Language :: Python :: 3
Classifier: License :: CC0 1.0 Universal (CC0 1.0) Public Domain Dedication
Classifier: Operating System :: OS Independent
Classifier: Topic :: Software Development :: Libraries :: Python Modules
Requires-Python: >=3.9
